MANIFEST.in
README.txt
setup.py
django_openid_provider.egg-info/PKG-INFO
django_openid_provider.egg-info/SOURCES.txt
django_openid_provider.egg-info/dependency_links.txt
django_openid_provider.egg-info/not-zip-safe
django_openid_provider.egg-info/top_level.txt
openid_provider/__init__.py
openid_provider/admin.py
openid_provider/conf.py
openid_provider/models.py
openid_provider/urls.py
openid_provider/utils.py
openid_provider/views.py
openid_provider/migrations/0001_initial.py
openid_provider/migrations/__init__.py
openid_provider/templates/openid_provider/base.html
openid_provider/templates/openid_provider/decide.html
openid_provider/templates/openid_provider/error.html
openid_provider/templates/openid_provider/response.html
openid_provider/templates/openid_provider/server.html
openid_provider/templates/openid_provider/xrds.xml