Metadata-Version: 1.1
Name: django-openid-provider
Version: 0.6
Summary: An OpenID provider for your django.contrib.auth accounts
Home-page: http://django-openid-provider.readthedocs.org/
Author: Roman Barczyński
Author-email: UNKNOWN
License: Apache
Download-URL: https://bitbucket.org/romke/django_openid_provider
Platform: UNKNOWN
Classifier: Development Status :: 3 - Alpha
Classifier: Environment :: Web Environment
Classifier: Intended Audience :: Developers
Classifier: License :: OSI Approved :: Apache Software License
Classifier: Operating System :: OS Independent
Classifier: Programming Language :: Python
Classifier: Framework :: Django
